vsce_tui/__init__.py
vsce_tui/cli.py
vsce_tui-0.1.1.dist-info/LICENSE
vsce_tui-0.1.1.dist-info/METADATA
vsce_tui-0.1.1.dist-info/WHEEL
vsce_tui-0.1.1.dist-info/entry_points.txt
vsce_tui-0.1.1.dist-info/top_level.txt
vsce_tui-0.1.1.dist-info/RECORD
