Metadata-Version: 2.2
Name: vsce_tui
Version: 0.1.1
Summary: A TUI tool for managing VS Code extensions.
Author-email: Your Name <your.email@example.com>
License: MIT License
Project-URL: Homepage, https://github.com/yourusername/vsce_tui
Classifier: Programming Language :: Python :: 3
Classifier: License :: OSI Approved :: MIT License
Classifier: Operating System :: POSIX :: Linux
Requires-Python: >=3.7
License-File: LICENSE
